drawsvg/__init__.py
drawsvg/color.py
drawsvg/defs.py
drawsvg/drawing.py
drawsvg/elements.py
drawsvg/font_embed.py
drawsvg/frame_animation.py
drawsvg/jupyter.py
drawsvg/raster.py
drawsvg/types.py
drawsvg/url_encode.py
drawsvg/video.py
drawsvg/native_animation/__init__.py
drawsvg/native_animation/playback_control_js.py
drawsvg/native_animation/playback_control_ui.py
drawsvg/native_animation/synced_animation.py
drawsvg/widgets/__init__.py
drawsvg/widgets/async_animation.py
drawsvg/widgets/drawing_javascript.py
drawsvg/widgets/drawing_widget.py
drawsvg-2.2.0.dist-info/LICENSE.txt
drawsvg-2.2.0.dist-info/METADATA
drawsvg-2.2.0.dist-info/WHEEL
drawsvg-2.2.0.dist-info/top_level.txt
drawsvg-2.2.0.dist-info/RECORD
