Metadata-Version: 2.1
Name: drawsvg
Version: 2.2.0
Summary: A Python 3 library for programmatically generating SVG (vector) images and animations.  Drawsvg can also render to PNG, MP4, and display your drawings in Jupyter notebook and Jupyter lab.
Home-page: https://github.com/cduck/drawsvg
Download-URL: https://github.com/cduck/drawsvg/archive/2.2.0.tar.gz
Author: Casey Duckering
Keywords: SVG,draw,graphics,iPython,Jupyter,widget,animation
Classifier: License :: OSI Approved :: MIT License
Classifier: Programming Language :: Python :: 3
Classifier: Framework :: IPython
Classifier: Framework :: Jupyter
License-File: LICENSE.txt
Provides-Extra: all
Requires-Dist: cairoSVG (~=2.3) ; extra == 'all'
Requires-Dist: numpy (~=1.16) ; extra == 'all'
Requires-Dist: imageio (~=2.5) ; extra == 'all'
Requires-Dist: imageio-ffmpeg (~=0.4) ; extra == 'all'
Requires-Dist: pwkit (~=1.0) ; extra == 'all'
Provides-Extra: color
Requires-Dist: pwkit (~=1.0) ; extra == 'color'
Requires-Dist: numpy (~=1.16) ; extra == 'color'
Provides-Extra: raster
Requires-Dist: cairoSVG (~=2.3) ; extra == 'raster'
Requires-Dist: numpy (~=1.16) ; extra == 'raster'
Requires-Dist: imageio (~=2.5) ; extra == 'raster'
Requires-Dist: imageio-ffmpeg (~=0.4) ; extra == 'raster'
